docfx_yaml/__init__.py
docfx_yaml/directives.py
docfx_yaml/extension.py
docfx_yaml/extract_nodes.py
docfx_yaml/monkeypatch.py
docfx_yaml/nodes.py
docfx_yaml/settings.py
docfx_yaml/utils.py
docfx_yaml/writer.py
sphinx_docfx_yaml-1.2.40.dist-info/METADATA
sphinx_docfx_yaml-1.2.40.dist-info/RECORD
sphinx_docfx_yaml-1.2.40.dist-info/WHEEL
sphinx_docfx_yaml-1.2.40.dist-info/top_level.txt
