Metadata-Version: 2.1
Name: sphinx-docfx-yaml
Version: 1.2.40
Summary: Sphinx Python Domain to DocFX YAML Generator
Home-page: https://github.com/ericholscher/sphinx-docfx-yaml
Author: Eric Holscher
Author-email: eric@ericholscher.com
License: UNKNOWN
Platform: UNKNOWN
Requires-Dist: PyYAML
Requires-Dist: wheel (>=0.24.0)
Requires-Dist: sphinx (==1.5.5)
Requires-Dist: unidecode
